<?xml version="1.0" encoding="utf-8"?><RailWay><StopLocations><StopLocation location="175000" start_coordinate="0" end_coordinate="350000" capacity="2" /><StopLocation location="525000" start_coordinate="350000" end_coordinate="700000" capacity="2" /><StopLocation location="2507400" start_coordinate="2332400" end_coordinate="2682400" capacity="2" /><StopLocation location="2887400" start_coordinate="2712400" end_coordinate="3062400" capacity="4" /><StopLocation location="3237400" start_coordinate="3062400" end_coordinate="3412400" capacity="4" /><StopLocation location="3617400" start_coordinate="3442400" end_coordinate="3792400" capacity="3" /><StopLocation location="3967400" start_coordinate="3792400" end_coordinate="4142400" capacity="3" /><StopLocation location="6136600" start_coordinate="5961600" end_coordinate="6311600" capacity="4" /><StopLocation location="6486600" start_coordinate="6311600" end_coordinate="6661600" capacity="4" /><StopLocation location="6836600" start_coordinate="6661600" end_coordinate="7011600" capacity="4" /><StopLocation location="7186600" start_coordinate="7011600" end_coordinate="7361600" capacity="4" /><StopLocation location="7536600" start_coordinate="7361600" end_coordinate="7711600" capacity="4" /><StopLocation location="7916600" start_coordinate="7741600" end_coordinate="8091600" capacity="2" /><StopLocation location="8296600" start_coordinate="8121600" end_coordinate="8471600" capacity="2" /><StopLocation location="8646600" start_coordinate="8471600" end_coordinate="8821600" capacity="2" /><StopLocation location="8996600" start_coordinate="8821600" end_coordinate="9171600" capacity="2" /><StopLocation location="10951100" start_coordinate="10776100" end_coordinate="11126100" capacity="2" /><StopLocation location="13185000" start_coordinate="13010000" end_coordinate="13360000" capacity="4" /><StopLocation location="14782900" start_coordinate="14607900" end_coordinate="14957900" capacity="2" /><StopLocation location="17015700" start_coordinate="16840700" end_coordinate="17190700" capacity="2" /><StopLocation location="17365700" start_coordinate="17190700" end_coordinate="17540700" capacity="2" /><StopLocation location="17715700" start_coordinate="17540700" end_coordinate="17890700" capacity="2" /><StopLocation location="18065700" start_coordinate="17890700" end_coordinate="18240700" capacity="2" /><StopLocation location="18415700" start_coordinate="18240700" end_coordinate="18590700" capacity="2" /><StopLocation location="18795700" start_coordinate="18620700" end_coordinate="18970700" capacity="2" /><StopLocation location="19175700" start_coordinate="19000700" end_coordinate="19350700" capacity="2" /><StopLocation location="19525700" start_coordinate="19350700" end_coordinate="19700700" capacity="2" /><StopLocation location="21247400" start_coordinate="21072400" end_coordinate="21422400" capacity="2" /><StopLocation location="21627400" start_coordinate="21452400" end_coordinate="21802400" capacity="2" /><StopLocation location="21977400" start_coordinate="21802400" end_coordinate="22152400" capacity="2" /><StopLocation location="22327400" start_coordinate="22152400" end_coordinate="22502400" capacity="2" /><StopLocation location="22677400" start_coordinate="22502400" end_coordinate="22852400" capacity="2" /><StopLocation location="24975200" start_coordinate="24800200" end_coordinate="25150200" capacity="3" /><StopLocation location="25355200" start_coordinate="25180200" end_coordinate="25530200" capacity="4" /><StopLocation location="27670100" start_coordinate="27495100" end_coordinate="27845100" capacity="2" /><StopLocation location="28020100" start_coordinate="27845100" end_coordinate="28195100" capacity="2" /><StopLocation location="28400100" start_coordinate="28225100" end_coordinate="28575100" capacity="3" /><StopLocation location="30192000" start_coordinate="30017000" end_coordinate="30367000" capacity="4" /><StopLocation location="30542000" start_coordinate="30367000" end_coordinate="30717000" capacity="4" /><StopLocation location="30892000" start_coordinate="30717000" end_coordinate="31067000" capacity="4" /><StopLocation location="31242000" start_coordinate="31067000" end_coordinate="31417000" capacity="4" /><StopLocation location="31592000" start_coordinate="31417000" end_coordinate="31767000" capacity="4" /><StopLocation location="31972000" start_coordinate="31797000" end_coordinate="32147000" capacity="3" /><StopLocation location="32322000" start_coordinate="32147000" end_coordinate="32497000" capacity="3" /><StopLocation location="34534400" start_coordinate="34359400" end_coordinate="34709400" capacity="2" /><StopLocation location="36152000" start_coordinate="35977000" end_coordinate="36327000" capacity="3" /><StopLocation location="36532000" start_coordinate="36357000" end_coordinate="36707000" capacity="2" /><StopLocation location="36912000" start_coordinate="36737000" end_coordinate="37087000" capacity="4" /><StopLocation location="37292000" start_coordinate="37117000" end_coordinate="37467000" capacity="2" /><StopLocation location="39227000" start_coordinate="39052000" end_coordinate="39402000" capacity="2" /><StopLocation location="41493100" start_coordinate="41318100" end_coordinate="41668100" capacity="2" /><StopLocation location="41843100" start_coordinate="41668100" end_coordinate="42018100" capacity="2" /><StopLocation location="43509600" start_coordinate="43334600" end_coordinate="43684600" capacity="3" /><StopLocation location="43859600" start_coordinate="43684600" end_coordinate="44034600" capacity="3" /><StopLocation location="44239600" start_coordinate="44064600" end_coordinate="44414600" capacity="3" /></StopLocations><Segments><Segment location="175000" start_coordinate="0" end_coordinate="350000" segment="CDV_1E1T" track="1" /><Segment location="175000" start_coordinate="0" end_coordinate="350000" segment="CDV_2E1T" track="2" /><Segment location="525000" start_coordinate="350000" end_coordinate="700000" segment="CDV_1E2T" track="1" /><Segment location="525000" start_coordinate="350000" end_coordinate="700000" segment="CDV_2E2T" track="2" /><Segment location="525000" start_coordinate="700000" end_coordinate="2332400" segment="WT" track="1" /><Segment location="2507400" start_coordinate="2332400" end_coordinate="2682400" segment="CDV_1E1T" track="1" /><Segment location="2507400" start_coordinate="2332400" end_coordinate="2682400" segment="CDV_2E1T" track="2" /><Segment location="2507400" start_coordinate="2682400" end_coordinate="2712400" segment="WT" track="1" /><Segment location="2887400" start_coordinate="2712400" end_coordinate="3062400" segment="CDV_1E1T" track="1" /><Segment location="2887400" start_coordinate="2712400" end_coordinate="3062400" segment="CDV_2E1T" track="2" /><Segment location="2887400" start_coordinate="2712400" end_coordinate="3062400" segment="CDV_3E1T" track="3" /><Segment location="2887400" start_coordinate="2712400" end_coordinate="3062400" segment="CDV_4E1T" track="4" /><Segment location="3237400" start_coordinate="3062400" end_coordinate="3412400" segment="CDV_1E2T" track="1" /><Segment location="3237400" start_coordinate="3062400" end_coordinate="3412400" segment="CDV_2E2T" track="2" /><Segment location="3237400" start_coordinate="3062400" end_coordinate="3412400" segment="CDV_3E2T" track="3" /><Segment location="3237400" start_coordinate="3062400" end_coordinate="3412400" segment="CDV_4E2T" track="4" /><Segment location="3237400" start_coordinate="3412400" end_coordinate="3442400" segment="WT" track="1" /><Segment location="3617400" start_coordinate="3442400" end_coordinate="3792400" segment="CDV_1E1T" track="1" /><Segment location="3617400" start_coordinate="3442400" end_coordinate="3792400" segment="CDV_2E1T" track="2" /><Segment location="3617400" start_coordinate="3442400" end_coordinate="3792400" segment="CDV_3E1T" track="3" /><Segment location="3967400" start_coordinate="3792400" end_coordinate="4142400" segment="CDV_1E2T" track="1" /><Segment location="3967400" start_coordinate="3792400" end_coordinate="4142400" segment="CDV_2E2T" track="2" /><Segment location="3967400" start_coordinate="3792400" end_coordinate="4142400" segment="CDV_3E2T" track="3" /><Segment location="3967400" start_coordinate="4142400" end_coordinate="5961600" segment="WT" track="1" /><Segment location="6136600" start_coordinate="5961600" end_coordinate="6311600" segment="CDV_1E1T" track="1" /><Segment location="6136600" start_coordinate="5961600" end_coordinate="6311600" segment="CDV_2E1T" track="2" /><Segment location="6136600" start_coordinate="5961600" end_coordinate="6311600" segment="CDV_3E1T" track="3" /><Segment location="6136600" start_coordinate="5961600" end_coordinate="6311600" segment="CDV_4E1T" track="4" /><Segment location="6486600" start_coordinate="6311600" end_coordinate="6661600" segment="CDV_1E2T" track="1" /><Segment location="6486600" start_coordinate="6311600" end_coordinate="6661600" segment="CDV_2E2T" track="2" /><Segment location="6486600" start_coordinate="6311600" end_coordinate="6661600" segment="CDV_3E2T" track="3" /><Segment location="6486600" start_coordinate="6311600" end_coordinate="6661600" segment="CDV_4E2T" track="4" /><Segment location="6836600" start_coordinate="6661600" end_coordinate="7011600" segment="CDV_1E3T" track="1" /><Segment location="6836600" start_coordinate="6661600" end_coordinate="7011600" segment="CDV_2E3T" track="2" /><Segment location="6836600" start_coordinate="6661600" end_coordinate="7011600" segment="CDV_3E3T" track="3" /><Segment location="6836600" start_coordinate="6661600" end_coordinate="7011600" segment="CDV_4E3T" track="4" /><Segment location="7186600" start_coordinate="7011600" end_coordinate="7361600" segment="CDV_1E4T" track="1" /><Segment location="7186600" start_coordinate="7011600" end_coordinate="7361600" segment="CDV_2E4T" track="2" /><Segment location="7186600" start_coordinate="7011600" end_coordinate="7361600" segment="CDV_3E4T" track="3" /><Segment location="7186600" start_coordinate="7011600" end_coordinate="7361600" segment="CDV_4E4T" track="4" /><Segment location="7536600" start_coordinate="7361600" end_coordinate="7711600" segment="CDV_1E5T" track="1" /><Segment location="7536600" start_coordinate="7361600" end_coordinate="7711600" segment="CDV_2E5T" track="2" /><Segment location="7536600" start_coordinate="7361600" end_coordinate="7711600" segment="CDV_3E5T" track="3" /><Segment location="7536600" start_coordinate="7361600" end_coordinate="7711600" segment="CDV_4E5T" track="4" /><Segment location="7536600" start_coordinate="7711600" end_coordinate="7741600" segment="WT" track="1" /><Segment location="7916600" start_coordinate="7741600" end_coordinate="8091600" segment="CDV_1E1T" track="1" /><Segment location="7916600" start_coordinate="7741600" end_coordinate="8091600" segment="CDV_2E1T" track="2" /><Segment location="7916600" start_coordinate="8091600" end_coordinate="8121600" segment="WT" track="1" /><Segment location="8296600" start_coordinate="8121600" end_coordinate="8471600" segment="CDV_1E1T" track="1" /><Segment location="8296600" start_coordinate="8121600" end_coordinate="8471600" segment="CDV_2E1T" track="2" /><Segment location="8646600" start_coordinate="8471600" end_coordinate="8821600" segment="CDV_1E2T" track="1" /><Segment location="8646600" start_coordinate="8471600" end_coordinate="8821600" segment="CDV_2E2T" track="2" /><Segment location="8996600" start_coordinate="8821600" end_coordinate="9171600" segment="CDV_1E3T" track="1" /><Segment location="8996600" start_coordinate="8821600" end_coordinate="9171600" segment="CDV_2E3T" track="2" /><Segment location="8996600" start_coordinate="9171600" end_coordinate="10776100" segment="WT" track="1" /><Segment location="10951100" start_coordinate="10776100" end_coordinate="11126100" segment="CDV_1E1T" track="1" /><Segment location="10951100" start_coordinate="10776100" end_coordinate="11126100" segment="CDV_2E1T" track="2" /><Segment location="10951100" start_coordinate="11126100" end_coordinate="13010000" segment="WT" track="1" /><Segment location="13185000" start_coordinate="13010000" end_coordinate="13360000" segment="CDV_1E1T" track="1" /><Segment location="13185000" start_coordinate="13010000" end_coordinate="13360000" segment="CDV_2E1T" track="2" /><Segment location="13185000" start_coordinate="13010000" end_coordinate="13360000" segment="CDV_3E1T" track="3" /><Segment location="13185000" start_coordinate="13010000" end_coordinate="13360000" segment="CDV_4E1T" track="4" /><Segment location="13185000" start_coordinate="13360000" end_coordinate="14607900" segment="WT" track="1" /><Segment location="14782900" start_coordinate="14607900" end_coordinate="14957900" segment="CDV_1E1T" track="1" /><Segment location="14782900" start_coordinate="14607900" end_coordinate="14957900" segment="CDV_2E1T" track="2" /><Segment location="14782900" start_coordinate="14957900" end_coordinate="16840700" segment="WT" track="1" /><Segment location="17015700" start_coordinate="16840700" end_coordinate="17190700" segment="CDV_1E1T" track="1" /><Segment location="17015700" start_coordinate="16840700" end_coordinate="17190700" segment="CDV_2E1T" track="2" /><Segment location="17365700" start_coordinate="17190700" end_coordinate="17540700" segment="CDV_1E2T" track="1" /><Segment location="17365700" start_coordinate="17190700" end_coordinate="17540700" segment="CDV_2E2T" track="2" /><Segment location="17715700" start_coordinate="17540700" end_coordinate="17890700" segment="CDV_1E3T" track="1" /><Segment location="17715700" start_coordinate="17540700" end_coordinate="17890700" segment="CDV_2E3T" track="2" /><Segment location="18065700" start_coordinate="17890700" end_coordinate="18240700" segment="CDV_1E4T" track="1" /><Segment location="18065700" start_coordinate="17890700" end_coordinate="18240700" segment="CDV_2E4T" track="2" /><Segment location="18415700" start_coordinate="18240700" end_coordinate="18590700" segment="CDV_1E5T" track="1" /><Segment location="18415700" start_coordinate="18240700" end_coordinate="18590700" segment="CDV_2E5T" track="2" /><Segment location="18415700" start_coordinate="18590700" end_coordinate="18620700" segment="WT" track="1" /><Segment location="18795700" start_coordinate="18620700" end_coordinate="18970700" segment="CDV_1E1T" track="1" /><Segment location="18795700" start_coordinate="18620700" end_coordinate="18970700" segment="CDV_2E1T" track="2" /><Segment location="18795700" start_coordinate="18970700" end_coordinate="19000700" segment="WT" track="1" /><Segment location="19175700" start_coordinate="19000700" end_coordinate="19350700" segment="CDV_1E1T" track="1" /><Segment location="19175700" start_coordinate="19000700" end_coordinate="19350700" segment="CDV_2E1T" track="2" /><Segment location="19525700" start_coordinate="19350700" end_coordinate="19700700" segment="CDV_1E2T" track="1" /><Segment location="19525700" start_coordinate="19350700" end_coordinate="19700700" segment="CDV_2E2T" track="2" /><Segment location="19525700" start_coordinate="19700700" end_coordinate="21072400" segment="WT" track="1" /><Segment location="21247400" start_coordinate="21072400" end_coordinate="21422400" segment="CDV_1E1T" track="1" /><Segment location="21247400" start_coordinate="21072400" end_coordinate="21422400" segment="CDV_2E1T" track="2" /><Segment location="21247400" start_coordinate="21422400" end_coordinate="21452400" segment="WT" track="1" /><Segment location="21627400" start_coordinate="21452400" end_coordinate="21802400" segment="CDV_1E1T" track="1" /><Segment location="21627400" start_coordinate="21452400" end_coordinate="21802400" segment="CDV_2E1T" track="2" /><Segment location="21977400" start_coordinate="21802400" end_coordinate="22152400" segment="CDV_1E2T" track="1" /><Segment location="21977400" start_coordinate="21802400" end_coordinate="22152400" segment="CDV_2E2T" track="2" /><Segment location="22327400" start_coordinate="22152400" end_coordinate="22502400" segment="CDV_1E3T" track="1" /><Segment location="22327400" start_coordinate="22152400" end_coordinate="22502400" segment="CDV_2E3T" track="2" /><Segment location="22677400" start_coordinate="22502400" end_coordinate="22852400" segment="CDV_1E4T" track="1" /><Segment location="22677400" start_coordinate="22502400" end_coordinate="22852400" segment="CDV_2E4T" track="2" /><Segment location="22677400" start_coordinate="22852400" end_coordinate="24800200" segment="WT" track="1" /><Segment location="24975200" start_coordinate="24800200" end_coordinate="25150200" segment="CDV_1E1T" track="1" /><Segment location="24975200" start_coordinate="24800200" end_coordinate="25150200" segment="CDV_2E1T" track="2" /><Segment location="24975200" start_coordinate="24800200" end_coordinate="25150200" segment="CDV_3E1T" track="3" /><Segment location="24975200" start_coordinate="25150200" end_coordinate="25180200" segment="WT" track="1" /><Segment location="25355200" start_coordinate="25180200" end_coordinate="25530200" segment="CDV_1E1T" track="1" /><Segment location="25355200" start_coordinate="25180200" end_coordinate="25530200" segment="CDV_2E1T" track="2" /><Segment location="25355200" start_coordinate="25180200" end_coordinate="25530200" segment="CDV_3E1T" track="3" /><Segment location="25355200" start_coordinate="25180200" end_coordinate="25530200" segment="CDV_4E1T" track="4" /><Segment location="25355200" start_coordinate="25530200" end_coordinate="27495100" segment="WT" track="1" /><Segment location="27670100" start_coordinate="27495100" end_coordinate="27845100" segment="CDV_1E1T" track="1" /><Segment location="27670100" start_coordinate="27495100" end_coordinate="27845100" segment="CDV_2E1T" track="2" /><Segment location="28020100" start_coordinate="27845100" end_coordinate="28195100" segment="CDV_1E2T" track="1" /><Segment location="28020100" start_coordinate="27845100" end_coordinate="28195100" segment="CDV_2E2T" track="2" /><Segment location="28020100" start_coordinate="28195100" end_coordinate="28225100" segment="WT" track="1" /><Segment location="28400100" start_coordinate="28225100" end_coordinate="28575100" segment="CDV_1E1T" track="1" /><Segment location="28400100" start_coordinate="28225100" end_coordinate="28575100" segment="CDV_2E1T" track="2" /><Segment location="28400100" start_coordinate="28225100" end_coordinate="28575100" segment="CDV_3E1T" track="3" /><Segment location="28400100" start_coordinate="28575100" end_coordinate="30017000" segment="WT" track="1" /><Segment location="30192000" start_coordinate="30017000" end_coordinate="30367000" segment="CDV_1E1T" track="1" /><Segment location="30192000" start_coordinate="30017000" end_coordinate="30367000" segment="CDV_2E1T" track="2" /><Segment location="30192000" start_coordinate="30017000" end_coordinate="30367000" segment="CDV_3E1T" track="3" /><Segment location="30192000" start_coordinate="30017000" end_coordinate="30367000" segment="CDV_4E1T" track="4" /><Segment location="30542000" start_coordinate="30367000" end_coordinate="30717000" segment="CDV_1E2T" track="1" /><Segment location="30542000" start_coordinate="30367000" end_coordinate="30717000" segment="CDV_2E2T" track="2" /><Segment location="30542000" start_coordinate="30367000" end_coordinate="30717000" segment="CDV_3E2T" track="3" /><Segment location="30542000" start_coordinate="30367000" end_coordinate="30717000" segment="CDV_4E2T" track="4" /><Segment location="30892000" start_coordinate="30717000" end_coordinate="31067000" segment="CDV_1E3T" track="1" /><Segment location="30892000" start_coordinate="30717000" end_coordinate="31067000" segment="CDV_2E3T" track="2" /><Segment location="30892000" start_coordinate="30717000" end_coordinate="31067000" segment="CDV_3E3T" track="3" /><Segment location="30892000" start_coordinate="30717000" end_coordinate="31067000" segment="CDV_4E3T" track="4" /><Segment location="31242000" start_coordinate="31067000" end_coordinate="31417000" segment="CDV_1E4T" track="1" /><Segment location="31242000" start_coordinate="31067000" end_coordinate="31417000" segment="CDV_2E4T" track="2" /><Segment location="31242000" start_coordinate="31067000" end_coordinate="31417000" segment="CDV_3E4T" track="3" /><Segment location="31242000" start_coordinate="31067000" end_coordinate="31417000" segment="CDV_4E4T" track="4" /><Segment location="31592000" start_coordinate="31417000" end_coordinate="31767000" segment="CDV_1E5T" track="1" /><Segment location="31592000" start_coordinate="31417000" end_coordinate="31767000" segment="CDV_2E5T" track="2" /><Segment location="31592000" start_coordinate="31417000" end_coordinate="31767000" segment="CDV_3E5T" track="3" /><Segment location="31592000" start_coordinate="31417000" end_coordinate="31767000" segment="CDV_4E5T" track="4" /><Segment location="31592000" start_coordinate="31767000" end_coordinate="31797000" segment="WT" track="1" /><Segment location="31972000" start_coordinate="31797000" end_coordinate="32147000" segment="CDV_1E1T" track="1" /><Segment location="31972000" start_coordinate="31797000" end_coordinate="32147000" segment="CDV_2E1T" track="2" /><Segment location="31972000" start_coordinate="31797000" end_coordinate="32147000" segment="CDV_3E1T" track="3" /><Segment location="32322000" start_coordinate="32147000" end_coordinate="32497000" segment="CDV_1E2T" track="1" /><Segment location="32322000" start_coordinate="32147000" end_coordinate="32497000" segment="CDV_2E2T" track="2" /><Segment location="32322000" start_coordinate="32147000" end_coordinate="32497000" segment="CDV_3E2T" track="3" /><Segment location="32322000" start_coordinate="32497000" end_coordinate="34359400" segment="WT" track="1" /><Segment location="34534400" start_coordinate="34359400" end_coordinate="34709400" segment="CDV_1E1T" track="1" /><Segment location="34534400" start_coordinate="34359400" end_coordinate="34709400" segment="CDV_2E1T" track="2" /><Segment location="34534400" start_coordinate="34709400" end_coordinate="35977000" segment="WT" track="1" /><Segment location="36152000" start_coordinate="35977000" end_coordinate="36327000" segment="CDV_1E1T" track="1" /><Segment location="36152000" start_coordinate="35977000" end_coordinate="36327000" segment="CDV_2E1T" track="2" /><Segment location="36152000" start_coordinate="35977000" end_coordinate="36327000" segment="CDV_3E1T" track="3" /><Segment location="36152000" start_coordinate="36327000" end_coordinate="36357000" segment="WT" track="1" /><Segment location="36532000" start_coordinate="36357000" end_coordinate="36707000" segment="CDV_1E1T" track="1" /><Segment location="36532000" start_coordinate="36357000" end_coordinate="36707000" segment="CDV_2E1T" track="2" /><Segment location="36532000" start_coordinate="36707000" end_coordinate="36737000" segment="WT" track="1" /><Segment location="36912000" start_coordinate="36737000" end_coordinate="37087000" segment="CDV_1E1T" track="1" /><Segment location="36912000" start_coordinate="36737000" end_coordinate="37087000" segment="CDV_2E1T" track="2" /><Segment location="36912000" start_coordinate="36737000" end_coordinate="37087000" segment="CDV_3E1T" track="3" /><Segment location="36912000" start_coordinate="36737000" end_coordinate="37087000" segment="CDV_4E1T" track="4" /><Segment location="36912000" start_coordinate="37087000" end_coordinate="37117000" segment="WT" track="1" /><Segment location="37292000" start_coordinate="37117000" end_coordinate="37467000" segment="CDV_1E1T" track="1" /><Segment location="37292000" start_coordinate="37117000" end_coordinate="37467000" segment="CDV_2E1T" track="2" /><Segment location="37292000" start_coordinate="37467000" end_coordinate="39052000" segment="WT" track="1" /><Segment location="39227000" start_coordinate="39052000" end_coordinate="39402000" segment="CDV_1E1T" track="1" /><Segment location="39227000" start_coordinate="39052000" end_coordinate="39402000" segment="CDV_2E1T" track="2" /><Segment location="39227000" start_coordinate="39402000" end_coordinate="41318100" segment="WT" track="1" /><Segment location="41493100" start_coordinate="41318100" end_coordinate="41668100" segment="CDV_1E1T" track="1" /><Segment location="41493100" start_coordinate="41318100" end_coordinate="41668100" segment="CDV_2E1T" track="2" /><Segment location="41843100" start_coordinate="41668100" end_coordinate="42018100" segment="CDV_1E2T" track="1" /><Segment location="41843100" start_coordinate="41668100" end_coordinate="42018100" segment="CDV_2E2T" track="2" /><Segment location="41843100" start_coordinate="42018100" end_coordinate="43334600" segment="WT" track="1" /><Segment location="43509600" start_coordinate="43334600" end_coordinate="43684600" segment="CDV_1E1T" track="1" /><Segment location="43509600" start_coordinate="43334600" end_coordinate="43684600" segment="CDV_2E1T" track="2" /><Segment location="43509600" start_coordinate="43334600" end_coordinate="43684600" segment="CDV_3E1T" track="3" /><Segment location="43859600" start_coordinate="43684600" end_coordinate="44034600" segment="CDV_1E2T" track="1" /><Segment location="43859600" start_coordinate="43684600" end_coordinate="44034600" segment="CDV_2E2T" track="2" /><Segment location="43859600" start_coordinate="43684600" end_coordinate="44034600" segment="CDV_3E2T" track="3" /><Segment location="43859600" start_coordinate="44034600" end_coordinate="44064600" segment="WT" track="1" /><Segment location="44239600" start_coordinate="44064600" end_coordinate="44414600" segment="CDV_1E1T" track="1" /><Segment location="44239600" start_coordinate="44064600" end_coordinate="44414600" segment="CDV_2E1T" track="2" /><Segment location="44239600" start_coordinate="44064600" end_coordinate="44414600" segment="CDV_3E1T" track="3" /><Segment location="44239600" start_coordinate="44414600" end_coordinate="44444600" segment="WT" track="1" /></Segments><Interdictions /><PATs /><TrainPerformances /><Trains><Train train_id="1" name="T1" data_ocup="28/12/2015 17:58:55" location="175000" ud="CDV_1E1T" direction="1" track="1" coordinate="0" origem="350000" destino="44414600" departure_time="26/12/2015 08:29:12" /><Train train_id="3" name="T3" data_ocup="28/12/2015 17:58:55" location="36912000" ud="CDV_4E1T" direction="1" track="4" coordinate="36737000" origem="350000" destino="44414600" departure_time="26/12/2015 14:37:50" /><Train train_id="4" name="T4" data_ocup="28/12/2015 17:58:55" location="36912000" ud="CDV_3E1T" direction="1" track="3" coordinate="36737000" origem="350000" destino="44414600" departure_time="26/12/2015 17:48:33" /><Train train_id="5" name="T5" data_ocup="28/12/2015 17:58:55" location="36532000" ud="CDV_1E1T" direction="1" track="1" coordinate="36357000" origem="350000" destino="44414600" departure_time="26/12/2015 22:46:20" /><Train train_id="6" name="T6" data_ocup="28/12/2015 17:58:55" location="6486600" ud="CDV_3E2T" direction="1" track="3" coordinate="6311600" origem="350000" destino="44414600" departure_time="26/12/2015 21:59:06" /><Train train_id="7" name="T7" data_ocup="28/12/2015 17:58:55" location="30542000" ud="CDV_1E2T" direction="-1" track="1" coordinate="30717000" origem="44444600" destino="0" departure_time="27/12/2015 12:53:14" /><Train train_id="8" name="T8" data_ocup="28/12/2015 17:58:55" location="31242000" ud="CDV_2E4T" direction="1" track="2" coordinate="31067000" origem="350000" destino="44414600" departure_time="26/12/2015 08:45:34" /><Train train_id="10" name="T10" data_ocup="28/12/2015 17:58:55" location="525000" ud="CDV_2E2T" direction="-1" track="2" coordinate="700000" origem="44444600" destino="0" departure_time="26/12/2015 00:27:10" /><Train train_id="11" name="T11" data_ocup="28/12/2015 17:58:55" location="7186600" ud="CDV_3E4T" direction="1" track="3" coordinate="7011600" origem="350000" destino="44414600" departure_time="26/12/2015 13:04:37" /><Train train_id="12" name="T12" data_ocup="28/12/2015 17:58:55" location="36152000" ud="CDV_3E1T" direction="-1" track="3" coordinate="36327000" origem="44444600" destino="0" departure_time="26/12/2015 18:23:38" /><Train train_id="14" name="T14" data_ocup="28/12/2015 17:58:55" location="27670100" ud="CDV_1E1T" direction="-1" track="1" coordinate="27845100" origem="44444600" destino="0" departure_time="28/12/2015 03:34:51" /><Train train_id="16" name="T16" data_ocup="28/12/2015 17:58:55" location="3967400" ud="CDV_3E2T" direction="1" track="3" coordinate="3792400" origem="350000" destino="44414600" departure_time="26/12/2015 23:32:34" /><Train train_id="18" name="T18" data_ocup="28/12/2015 17:58:55" location="43859600" ud="CDV_3E2T" direction="-1" track="3" coordinate="44034600" origem="44444600" destino="0" departure_time="28/12/2015 12:18:08" /><Train train_id="20" name="T20" data_ocup="28/12/2015 17:58:55" location="31972000" ud="CDV_1E1T" direction="1" track="1" coordinate="31797000" origem="350000" destino="44414600" departure_time="26/12/2015 07:31:49" /><Train train_id="22" name="T22" data_ocup="28/12/2015 17:58:55" location="18065700" ud="CDV_1E4T" direction="1" track="1" coordinate="17890700" origem="350000" destino="44414600" departure_time="28/12/2015 03:27:22" /><Train train_id="24" name="T24" data_ocup="28/12/2015 17:58:55" location="6836600" ud="CDV_1E3T" direction="1" track="1" coordinate="6661600" origem="350000" destino="44414600" departure_time="28/12/2015 02:02:21" /><Train train_id="25" name="T25" data_ocup="28/12/2015 17:58:55" location="21627400" ud="CDV_2E1T" direction="-1" track="2" coordinate="21802400" origem="44444600" destino="0" departure_time="27/12/2015 13:12:36" /><Train train_id="26" name="T26" data_ocup="28/12/2015 17:58:55" location="41493100" ud="CDV_1E1T" direction="1" track="1" coordinate="41318100" origem="350000" destino="44414600" departure_time="27/12/2015 05:45:35" /><Train train_id="28" name="T28" data_ocup="28/12/2015 17:58:55" location="2887400" ud="CDV_4E1T" direction="-1" track="4" coordinate="3062400" origem="44444600" destino="0" departure_time="28/12/2015 08:20:51" /><Train train_id="29" name="T29" data_ocup="28/12/2015 17:58:55" location="43859600" ud="CDV_1E2T" direction="-1" track="1" coordinate="44034600" origem="44444600" destino="0" departure_time="28/12/2015 16:14:56" /></Trains><Plans><Plan plan_id="10001" train_name="P1" origem="44414600" destino="0" direction="-1" departure_time="28/12/2015 18:58:54" /><Plan plan_id="10002" train_name="P2" origem="0" destino="44414600" direction="1" departure_time="28/12/2015 19:58:54" /><Plan plan_id="10003" train_name="P3" origem="44414600" destino="0" direction="-1" departure_time="28/12/2015 20:58:54" /><Plan plan_id="10004" train_name="P4" origem="0" destino="44414600" direction="1" departure_time="28/12/2015 21:58:54" /><Plan plan_id="10005" train_name="P5" origem="44414600" destino="0" direction="-1" departure_time="28/12/2015 22:58:54" /><Plan plan_id="10006" train_name="P6" origem="0" destino="44414600" direction="1" departure_time="28/12/2015 23:58:54" /><Plan plan_id="10007" train_name="P7" origem="44414600" destino="0" direction="-1" departure_time="29/12/2015 00:58:54" /><Plan plan_id="10008" train_name="P8" origem="0" destino="44414600" direction="1" departure_time="29/12/2015 01:58:54" /><Plan plan_id="10009" train_name="P9" origem="44414600" destino="0" direction="-1" departure_time="29/12/2015 02:58:54" /><Plan plan_id="10010" train_name="P10" origem="0" destino="44414600" direction="1" departure_time="29/12/2015 03:58:54" /></Plans></RailWay>